loxwebsocket/__init__.py
loxwebsocket/const.py
loxwebsocket/encryption.py
loxwebsocket/exceptions.py
loxwebsocket/lox_ws_api.py
loxwebsocket/lxtoken.py
loxwebsocket/cython_modules/__init__.py
loxwebsocket/cython_modules/extractor.pyx
loxwebsocket/cython_modules/extractor_compatible.c
loxwebsocket/cython_modules/extractor_compatible.cp314t-win32.pyd
loxwebsocket/cython_modules/extractor_compatible.pyx
loxwebsocket/cython_modules/extractor_optimized.c
loxwebsocket/cython_modules/extractor_optimized.cp314t-win32.pyd
loxwebsocket/cython_modules/extractor_optimized.pyx
loxwebsocket/cython_modules/setup.py
loxwebsocket-0.5.2.dist-info/licenses/LICENSE
loxwebsocket-0.5.2.dist-info/METADATA
loxwebsocket-0.5.2.dist-info/WHEEL
loxwebsocket-0.5.2.dist-info/top_level.txt
loxwebsocket-0.5.2.dist-info/RECORD
