Metadata-Version: 2.4
Name: loxwebsocket
Version: 0.5.2
Summary: A Python library for connecting to Loxone Smart Home systems via WebSocket
Author-email: Jakob Gliwa <your.email@example.com>
License-Expression: MIT
Project-URL: Homepage, https://github.com/yourusername/loxwebsocket
Project-URL: Documentation, https://github.com/yourusername/loxwebsocket#readme
Project-URL: Repository, https://github.com/yourusername/loxwebsocket.git
Project-URL: Issues, https://github.com/yourusername/loxwebsocket/issues
Keywords: loxone,websocket,smart-home,automation
Classifier: Development Status :: 4 - Beta
Classifier: Intended Audience :: Developers
Classifier: Programming Language :: Python :: 3
Classifier: Programming Language :: Python :: 3.9
Classifier: Programming Language :: Python :: 3.10
Classifier: Programming Language :: Python :: 3.11
Classifier: Programming Language :: Python :: 3.12
Classifier: Topic :: Home Automation
Classifier: Topic :: Software Development :: Libraries :: Python Modules
Requires-Python: >=3.9
License-File: LICENSE
Requires-Dist: aiohttp>=3.13.3
Requires-Dist: orjson>=3.11.5
Requires-Dist: pycryptodome>=3.23.0
Requires-Dist: construct>=2.10.70
Requires-Dist: py-cpuinfo>=9.0.0
Provides-Extra: test
Requires-Dist: pytest>=7.4.0; extra == "test"
Requires-Dist: pytest-asyncio>=0.21.1; extra == "test"
Requires-Dist: pytest-cov>=4.1.0; extra == "test"
Provides-Extra: dev
Requires-Dist: pytest>=7.4.0; extra == "dev"
Requires-Dist: pytest-asyncio>=0.21.1; extra == "dev"
Requires-Dist: pytest-cov>=4.1.0; extra == "dev"
Requires-Dist: black>=22.0.0; extra == "dev"
Requires-Dist: isort>=5.0.0; extra == "dev"
Requires-Dist: mypy>=1.0.0; extra == "dev"
Provides-Extra: build
Requires-Dist: setuptools>=80.9.0; extra == "build"
Requires-Dist: Cython>=3.2.4; extra == "build"
Requires-Dist: wheel>=0.45.1; extra == "build"
Dynamic: license-file
